{
  "sourcePdf": "mla1-25-26-6.10-details.pdf",
  "financialYear": "2025-26",
  "batchLabel": "MLA-1",
  "budgetCrore": 6.1,
  "works": [
    {
      "sortOrder": 1,
      "workCode": null,
      "taluka": "Anushakti Nagar",
      "village": "Greater Mumbai",
      "ward": "144",
      "name": "Well work at Agarwadi Village, Mankhurd",
      "physicalStatus": "WC",
      "mlaRecommendationRef": "16/05/2025",
      "technicalSanctionRef": null,
      "technicalSanctionDate": "2025-05-27",
      "technicalSanctionAmountThousands": 2000.0,
      "administrativeSanctionAmountThousands": 2000.0
    },
    {
      "sortOrder": 2,
      "workCode": null,
      "taluka": "Anushakti Nagar",
      "village": "Greater Mumbai",
      "ward": "147",
      "name": "Construction of compound wall, grill, and gate work for the water tank near Bldg. No. 30, Suprabhat Society at RNA Park",
      "physicalStatus": "WC",
      "mlaRecommendationRef": "16/05/2025",
      "technicalSanctionRef": null,
      "technicalSanctionDate": "2025-05-27",
      "technicalSanctionAmountThousands": 2500.0,
      "administrativeSanctionAmountThousands": 2500.0
    },
    {
      "sortOrder": 3,
      "workCode": null,
      "taluka": "Anushakti Nagar",
      "village": "Greater Mumbai",
      "ward": "147",
      "name": "Construction of an open shed near Bldg. No. D/4, Maharashtra Ekta Society, R.N.A. Park, Vashi Naka",
      "physicalStatus": "WC",
      "mlaRecommendationRef": "16/05/2025",
      "technicalSanctionRef": null,
      "technicalSanctionDate": "2025-05-27",
      "technicalSanctionAmountThousands": 2000.0,
      "administrativeSanctionAmountThousands": 2000.0
    },
    {
      "sortOrder": 4,
      "workCode": null,
      "taluka": "Anushakti Nagar",
      "village": "Greater Mumbai",
      "ward": "147",
      "name": "Construction of an open shed, concreting, and tiling work near Building No. 6, 7, 8, 9, 10, MHADA Colony, Vashi Naka",
      "physicalStatus": "WC",
      "mlaRecommendationRef": "15/05/2025",
      "technicalSanctionRef": null,
      "technicalSanctionDate": "2025-05-27",
      "technicalSanctionAmountThousands": 2500.0,
      "administrativeSanctionAmountThousands": 2500.0
    },
    {
      "sortOrder": 5,
      "workCode": null,
      "taluka": "Anushakti Nagar",
      "village": "Greater Mumbai",
      "ward": "140",
      "name": "Concreting work at E-1 and E-2, Deonar Colony, Govandi",
      "physicalStatus": "WIP",
      "mlaRecommendationRef": "16/05/2025",
      "technicalSanctionRef": null,
      "technicalSanctionDate": "2025-05-27",
      "technicalSanctionAmountThousands": 2000.0,
      "administrativeSanctionAmountThousands": 2000.0
    },
    {
      "sortOrder": 6,
      "workCode": null,
      "taluka": "Anushakti Nagar",
      "village": "Greater Mumbai",
      "ward": "140",
      "name": "Sewage line laying and water pipeline work at E-2 and E-3, Deonar Colony, Govandi",
      "physicalStatus": "WC",
      "mlaRecommendationRef": "16/05/2025",
      "technicalSanctionRef": null,
      "technicalSanctionDate": "2025-05-27",
      "technicalSanctionAmountThousands": 2500.0,
      "administrativeSanctionAmountThousands": 2500.0
    },
    {
      "sortOrder": 7,
      "workCode": null,
      "taluka": "Anushakti Nagar",
      "village": "Greater Mumbai",
      "ward": "140",
      "name": "Concreting work near E-3 and E-4, Deonar Colony, Govandi",
      "physicalStatus": "WIP",
      "mlaRecommendationRef": "16/05/2025",
      "technicalSanctionRef": null,
      "technicalSanctionDate": "2025-05-27",
      "technicalSanctionAmountThousands": 2000.0,
      "administrativeSanctionAmountThousands": 2000.0
    },
    {
      "sortOrder": 8,
      "workCode": null,
      "taluka": "Anushakti Nagar",
      "village": "Greater Mumbai",
      "ward": "148",
      "name": "Renovation of women's toilet, drain, and footpath work at Prakash Nagar, L.U. Gadkari Marg",
      "physicalStatus": "WNS",
      "mlaRecommendationRef": "16/05/2025",
      "technicalSanctionRef": null,
      "technicalSanctionDate": "2025-05-27",
      "technicalSanctionAmountThousands": 2500.0,
      "administrativeSanctionAmountThousands": 2500.0
    },
    {
      "sortOrder": 9,
      "workCode": null,
      "taluka": "Anushakti Nagar",
      "village": "Greater Mumbai",
      "ward": "148",
      "name": "Construction of senior citizen (Katta) and open shed work at Prakash Nagar, L.U. Gadkari Marg",
      "physicalStatus": "WC",
      "mlaRecommendationRef": "16/05/2025",
      "technicalSanctionRef": null,
      "technicalSanctionDate": "2025-05-27",
      "technicalSanctionAmountThousands": 1500.0,
      "administrativeSanctionAmountThousands": 1500.0
    },
    {
      "sortOrder": 10,
      "workCode": null,
      "taluka": "Anushakti Nagar",
      "village": "Greater Mumbai",
      "ward": "148",
      "name": "Construction of a compound wall near Building No. 6, 7, 8, 9, Rock Line, Bharat Nagar, Vashi Naka, Chembur",
      "physicalStatus": "WNS",
      "mlaRecommendationRef": "16/05/2025",
      "technicalSanctionRef": null,
      "technicalSanctionDate": "2025-05-27",
      "technicalSanctionAmountThousands": 2500.0,
      "administrativeSanctionAmountThousands": 2500.0
    },
    {
      "sortOrder": 11,
      "workCode": null,
      "taluka": "Anushakti Nagar",
      "village": "Greater Mumbai",
      "ward": "143",
      "name": "Construction of a (Katta) near Sant Savatamaali Vegetable Market, adjacent to Khandoba Temple, Maharashtra Nagar, Mankhurd",
      "physicalStatus": "WIP",
      "mlaRecommendationRef": "16/05/2025",
      "technicalSanctionRef": null,
      "technicalSanctionDate": "2025-05-27",
      "technicalSanctionAmountThousands": 2500.0,
      "administrativeSanctionAmountThousands": 2500.0
    },
    {
      "sortOrder": 12,
      "workCode": null,
      "taluka": "Anushakti Nagar",
      "village": "Greater Mumbai",
      "ward": "143",
      "name": "Concreting work in front of Buddha Vihar near Subway, Maharashtra Nagar, Mankhurd",
      "physicalStatus": "WIP",
      "mlaRecommendationRef": "15/05/2025",
      "technicalSanctionRef": null,
      "technicalSanctionDate": "2025-05-27",
      "technicalSanctionAmountThousands": 2500.0,
      "administrativeSanctionAmountThousands": 2500.0
    },
    {
      "sortOrder": 13,
      "workCode": null,
      "taluka": "Anushakti Nagar",
      "village": "Greater Mumbai",
      "ward": "147",
      "name": "Construction of a 3-seated toilet, sewage line work near Ramzan Shah Baba Dargah, Baba Bawadi, Vashi Naka",
      "physicalStatus": "WC",
      "mlaRecommendationRef": "16/05/2025",
      "technicalSanctionRef": null,
      "technicalSanctionDate": "2025-05-27",
      "technicalSanctionAmountThousands": 2500.0,
      "administrativeSanctionAmountThousands": 2500.0
    },
    {
      "sortOrder": 14,
      "workCode": null,
      "taluka": "Anushakti Nagar",
      "village": "Greater Mumbai",
      "ward": "147",
      "name": "Concreting, drain, and footpath work near Rajgruha Society, R.N.A. Park, Vashi Naka",
      "physicalStatus": "WNS",
      "mlaRecommendationRef": "16/05/2025",
      "technicalSanctionRef": null,
      "technicalSanctionDate": "2025-05-27",
      "technicalSanctionAmountThousands": 2000.0,
      "administrativeSanctionAmountThousands": 2000.0
    },
    {
      "sortOrder": 15,
      "workCode": null,
      "taluka": "Anushakti Nagar",
      "village": "Greater Mumbai",
      "ward": "148",
      "name": "Construction of an open shed, stage, and tiling work at Raigad Chawl, Vishnu Nagar",
      "physicalStatus": "WIP",
      "mlaRecommendationRef": "16/05/2025",
      "technicalSanctionRef": null,
      "technicalSanctionDate": "2025-05-27",
      "technicalSanctionAmountThousands": 2500.0,
      "administrativeSanctionAmountThousands": 2500.0
    },
    {
      "sortOrder": 16,
      "workCode": null,
      "taluka": "Anushakti Nagar",
      "village": "Greater Mumbai",
      "ward": "146",
      "name": "Construction of a Samaj Mandir and supplying open gymnasium equipment near Rudreshwar Mitra Mandal, Shiv Temple, Vadavali Village, Chembur",
      "physicalStatus": "WIP",
      "mlaRecommendationRef": "16/05/2025",
      "technicalSanctionRef": null,
      "technicalSanctionDate": "2025-05-27",
      "technicalSanctionAmountThousands": 2500.0,
      "administrativeSanctionAmountThousands": 2500.0
    },
    {
      "sortOrder": 17,
      "workCode": null,
      "taluka": "Anushakti Nagar",
      "village": "Greater Mumbai",
      "ward": "147",
      "name": "Providing an open shed and benches near Vinay High School, MHADA Colony, Vashi Naka",
      "physicalStatus": "WC",
      "mlaRecommendationRef": "16/05/2025",
      "technicalSanctionRef": null,
      "technicalSanctionDate": "2025-05-27",
      "technicalSanctionAmountThousands": 2500.0,
      "administrativeSanctionAmountThousands": 2500.0
    },
    {
      "sortOrder": 18,
      "workCode": null,
      "taluka": "Anushakti Nagar",
      "village": "Greater Mumbai",
      "ward": "148",
      "name": "Construction of a Samaj Mandir near Shiv Mitra Mandal, Bhim Tekadi, Bharat Nagar",
      "physicalStatus": "WNS",
      "mlaRecommendationRef": "16/05/2025",
      "technicalSanctionRef": null,
      "technicalSanctionDate": "2025-05-27",
      "technicalSanctionAmountThousands": 2500.0,
      "administrativeSanctionAmountThousands": 2500.0
    },
    {
      "sortOrder": 19,
      "workCode": null,
      "taluka": "Anushakti Nagar",
      "village": "Greater Mumbai",
      "ward": "143",
      "name": "Construction of an open shed near Shri Sant Savatamaali Vegetable Market, Maharashtra Nagar, Mankhurd",
      "physicalStatus": "WIP",
      "mlaRecommendationRef": "16/05/2025",
      "technicalSanctionRef": null,
      "technicalSanctionDate": "2025-05-27",
      "technicalSanctionAmountThousands": 2500.0,
      "administrativeSanctionAmountThousands": 2500.0
    },
    {
      "sortOrder": 20,
      "workCode": null,
      "taluka": "Anushakti Nagar",
      "village": "Greater Mumbai",
      "ward": "147",
      "name": "Providing an open shed and Concreting work near Sangharsh Mitra Mandal, Bldg. No. 15, Kukreja Phase 1",
      "physicalStatus": "WNS",
      "mlaRecommendationRef": "16/05/2025",
      "technicalSanctionRef": null,
      "technicalSanctionDate": "2025-05-27",
      "technicalSanctionAmountThousands": 2500.0,
      "administrativeSanctionAmountThousands": 2500.0
    },
    {
      "sortOrder": 21,
      "workCode": null,
      "taluka": "Anushakti Nagar",
      "village": "Greater Mumbai",
      "ward": "147",
      "name": "Concreting, drain, and footpath work near Sardar Vallabhbhai Patel Society, R.N.A. Park, Vashi Naka",
      "physicalStatus": "WNS",
      "mlaRecommendationRef": "16/05/2025",
      "technicalSanctionRef": null,
      "technicalSanctionDate": "2025-05-27",
      "technicalSanctionAmountThousands": 2000.0,
      "administrativeSanctionAmountThousands": 2000.0
    },
    {
      "sortOrder": 22,
      "workCode": null,
      "taluka": "Anushakti Nagar",
      "village": "Greater Mumbai",
      "ward": "147",
      "name": "Constructing compound wall and installing paver blocks near Sahjeevan Society, Building No. 9, Rock Line, MHADA Colony, Vashi Naka",
      "physicalStatus": "WC",
      "mlaRecommendationRef": "16/05/2025",
      "technicalSanctionRef": null,
      "technicalSanctionDate": "2025-05-27",
      "technicalSanctionAmountThousands": 2500.0,
      "administrativeSanctionAmountThousands": 2500.0
    },
    {
      "sortOrder": 23,
      "workCode": null,
      "taluka": "Anushakti Nagar",
      "village": "Greater Mumbai",
      "ward": "148",
      "name": "Construction of a compound wall and an open shed near Sunder Society, Shiv Temple, Bharat Nagar, Vashi Naka",
      "physicalStatus": "WC",
      "mlaRecommendationRef": "16/05/2025",
      "technicalSanctionRef": null,
      "technicalSanctionDate": "2025-05-27",
      "technicalSanctionAmountThousands": 2500.0,
      "administrativeSanctionAmountThousands": 2500.0
    },
    {
      "sortOrder": 24,
      "workCode": null,
      "taluka": "Anushakti Nagar",
      "village": "Greater Mumbai",
      "ward": "140",
      "name": "Concreting and gate work at E-3, Deonar Colony, Govandi (SC/ST)",
      "physicalStatus": "WC",
      "mlaRecommendationRef": "16/05/2025",
      "technicalSanctionRef": null,
      "technicalSanctionDate": "2025-05-27",
      "technicalSanctionAmountThousands": 2500.0,
      "administrativeSanctionAmountThousands": 2500.0
    },
    {
      "sortOrder": 25,
      "workCode": null,
      "taluka": "Anushakti Nagar",
      "village": "Greater Mumbai",
      "ward": "143",
      "name": "Construction of a gymnasium near Navtarun Utkarsh Mandal, Maharashtra Nagar, Mankhurd (SC/ST)",
      "physicalStatus": "WC",
      "mlaRecommendationRef": "16/05/2025",
      "technicalSanctionRef": null,
      "technicalSanctionDate": "2025-05-27",
      "technicalSanctionAmountThousands": 2500.0,
      "administrativeSanctionAmountThousands": 2500.0
    },
    {
      "sortOrder": 26,
      "workCode": null,
      "taluka": "Anushakti Nagar",
      "village": "Greater Mumbai",
      "ward": "148",
      "name": "Construction of a Samaj Mandir near Buddha Vihar, Bhim Tekadi, Bharat Nagar (SC/ST)",
      "physicalStatus": "WNS",
      "mlaRecommendationRef": "16/05/2025",
      "technicalSanctionRef": null,
      "technicalSanctionDate": "2025-05-27",
      "technicalSanctionAmountThousands": 2500.0,
      "administrativeSanctionAmountThousands": 2500.0
    }
  ]
}
